x_code/__init__.py
x_code/cli.py
x_code/core.py
x_code-0.1.3.dist-info/METADATA
x_code-0.1.3.dist-info/WHEEL
x_code-0.1.3.dist-info/entry_points.txt
x_code-0.1.3.dist-info/top_level.txt
x_code-0.1.3.dist-info/RECORD
