Metadata-Version: 2.1
Name: x_code
Version: 0.1.3
Summary: A package for coding assistant.
Home-page: https://github.com/khajamuheeb/x_code
Author: KhajaMuheeb
Author-email: khaja.muheeb@fisclouds.com
License: MIT
Requires-Dist: requests
